web_logger/__init__.py
web_logger/browser.py
web_logger/http_server.py
web_logger/logger.py
web_logger/loggerException.py
web_logger/stoppableThread.py
web_logger/ws_server.py
web_logger-0.6.0.dist-info/LICENSE
web_logger-0.6.0.dist-info/METADATA
web_logger-0.6.0.dist-info/WHEEL
web_logger-0.6.0.dist-info/top_level.txt
web_logger-0.6.0.dist-info/RECORD
