Metadata-Version: 2.1
Name: web-logger
Version: 0.6.0
Summary: Logger from python to HTML
Home-page: https://github.com/aduh95/web_logger
Author: Antoine du Hamel
Author-email: duhamelantoine1995@gmail.com
License: MIT
Project-URL: Bug Tracker, https://github.com/aduh95/web_logger/issues
Project-URL: Source Code, https://github.com/aduh95/web_logger
Platform: UNKNOWN
Classifier: Programming Language :: Python :: 3
Classifier: License :: OSI Approved :: MIT License
Classifier: Operating System :: OS Independent
Requires-Python: >=3.7
License-File: LICENSE
Requires-Dist: websockets
